badrandom/__init__.py
badrandom-0.0.1.dist-info/LICENSE.txt
badrandom-0.0.1.dist-info/METADATA
badrandom-0.0.1.dist-info/WHEEL
badrandom-0.0.1.dist-info/top_level.txt
badrandom-0.0.1.dist-info/RECORD
